{
    "hls":[
   {
"id": "2266",
"title": "Hellas Verona Vs Empoli",
"img": "https://images.fotmob.com/image_resources/logo/teamlogo/9876_small.png",
"img1": "https://images.fotmob.com/image_resources/logo/teamlogo/8534_small.png",
"time": "28.5.2023 (5:00 PM)",
"url": "https://sports01.livnvess.com/live/stream-118582_lhd.m3u8?txSecret=53074da3a7cdf931e5715393765c871c&txTime=647a8bca",
"live":"1",
"type": "Premium Sever HD,Premium Sever SD",
"premium":"true",
"league": "Serie A"
}
        








    
    
    ]
   
   }
   
   
