{
    "hls":[
   
   
 
 
{
"id": "2266",
"title": "Al Taee Vs Al Nassr FC",
"img": "https://images.fotmob.com/image_resources/logo/teamlogo/101917_small.png",
"img1": "https://images.fotmob.com/image_resources/logo/teamlogo/101918_small.png",
"time": "17.5.2023 (1:00 AM)",
"url": "https://sports01.livnvess.com/live/stream-143449_lhd.m3u8?txSecret=b78181e02cf6a388e5a88548281e2293&txTime=646417bd,https://sports01.livnvess.com/live/stream-143449_lsd.m3u8?txSecret=b78181e02cf6a388e5a88548281e2293&txTime=646417bd,https://pull.juqihuo.com/live/stream-886721_lhd.m3u8?auth_key=1684281380-0-0-af439901a4ca6d96d7dcea344f471933,https://pull.juqihuo.com/live/stream-886721_lsd.m3u8?auth_key=1684281380-0-0-70a4bf32bb1f907b66f26fbf4aa38cea",
"live":"1",
"type": "HD1,SD1,HD2,SD2",
"premium":"true",
"league": "Saudi Arabia Premier League"
},




{
"id": "2266",
"title": "Inter Vs Milan",
"img": "https://images.fotmob.com/image_resources/logo/teamlogo/8636_small.png",
"img1": "https://images.fotmob.com/image_resources/logo/teamlogo/8564_small.png",
"time": "17.5.2023 (1:30 AM)",
"url": "",
"live":"1",
"type": "HD1,SD1,HD2,SD2",
"premium":"true",
"league": "Champions League"
}



    
    
    ]
   
   }
   
   
