{
    "hls":[
  {
"id": "2266",
"title": "Torino Vs Inter",
"img": "https://images.fotmob.com/image_resources/logo/teamlogo/9804_small.png",
"img1": "https://images.fotmob.com/image_resources/logo/teamlogo/8636_small.png",
"time": "3.6.2023 (11:00 PM)",
"url": "",
"live":"0",
"type": "Premium Sever HD,Premium Sever SD",
"premium":"true",
"league": "Serie A"
},


{
"id": "2266",
"title": "Manchester City Vs Manchester United",
"img": "https://images.fotmob.com/image_resources/logo/teamlogo/8456_small.png",
"img1": "https://images.fotmob.com/image_resources/logo/teamlogo/10260_small.png",
"time": "3.6.2023 (8:30 PM)",
"url": "",
"live":"0",
"type": "Premium Sever HD,Premium Sever SD",
"premium":"true",
"league": "FA Cup"
},


{
"id": "2266",
"title": "Cremonese Vs Salernitana",
"img": "https://images.fotmob.com/image_resources/logo/teamlogo/7801_small.png",
"img1": "https://images.fotmob.com/image_resources/logo/teamlogo/6480_small.png",
"time": "4.6.2023 (1:30 AM)",
"url": "",
"live":"0",
"type": "Premium Sever HD,Premium Sever SD",
"premium":"true",
"league": "Serie A"
},


{
"id": "2266",
"title": "Cremonese Vs Salernitana",
"img": "https://images.fotmob.com/image_resources/logo/teamlogo/7801_small.png",
"img1": "https://images.fotmob.com/image_resources/logo/teamlogo/6480_small.png",
"time": "4.6.2023 (1:30 AM)",
"url": "",
"live":"0",
"type": "Premium Sever HD,Premium Sever SD",
"premium":"true",
"league": "Serie A"
},


{
"id": "2266",
"title": "Empoli Vs Lazio",
"img": "https://images.fotmob.com/image_resources/logo/teamlogo/8534_small.png",
"img1": "https://images.fotmob.com/image_resources/logo/teamlogo/8543_small.png",
"time": "4.6.2023 (1:30 AM)",
"url": "",
"live":"0",
"type": "Premium Sever HD,Premium Sever SD",
"premium":"true",
"league": "Serie A"
},


{
"id": "2266",
"title": "AC Ajaccio Vs Marseille",
"img": "https://images.fotmob.com/image_resources/logo/teamlogo/8576_small.png",
"img1": "https://images.fotmob.com/image_resources/logo/teamlogo/8592_small.png",
"time": "4.6.2023 (1:30 AM)",
"url": "",
"live":"0",
"type": "Premium Sever HD,Premium Sever SD",
"premium":"true",
"league": "Ligue 1"
},


{
"id": "2266",
"title": "Auxerre Vs Lens",
"img": "https://images.fotmob.com/image_resources/logo/teamlogo/8583_small.png",
"img1": "https://images.fotmob.com/image_resources/logo/teamlogo/8588_small.png",
"time": "4.6.2023 (1:30 AM)",
"url": "",
"live":"0",
"type": "Premium Sever HD,Premium Sever SD",
"premium":"true",
"league": "Ligue 1"
},


{
"id": "2266",
"title": "Brest Vs Rennes",
"img": "https://images.fotmob.com/image_resources/logo/teamlogo/8521_small.png",
"img1": "https://images.fotmob.com/image_resources/logo/teamlogo/9851_small.png",
"time": "4.6.2023 (1:30 AM)",
"url": "",
"live":"0",
"type": "Premium Sever HD,Premium Sever SD",
"premium":"true",
"league": "Ligue 1"
},


{
"id": "2266",
"title": "Lorient Vs Strasbourg",
"img": "https://images.fotmob.com/image_resources/logo/teamlogo/8689_small.png",
"img1": "https://images.fotmob.com/image_resources/logo/teamlogo/9848_small.png",
"time": "4.6.2023 (1:30 AM)",
"url": "",
"live":"0",
"type": "Premium Sever HD,Premium Sever SD",
"premium":"true",
"league": "Ligue 1"
},


{
"id": "2266",
"title": "Monaco Vs Toulouse",
"img": "https://images.fotmob.com/image_resources/logo/teamlogo/9829_small.png",
"img1": "https://images.fotmob.com/image_resources/logo/teamlogo/9941_small.png",
"time": "4.6.2023 (1:30 AM)",
"url": "",
"live":"0",
"type": "Premium Sever HD,Premium Sever SD",
"premium":"true",
"league": "Ligue 1"
},


{
"id": "2266",
"title": "Nantes Vs Angers",
"img": "https://images.fotmob.com/image_resources/logo/teamlogo/9830_small.png",
"img1": "https://images.fotmob.com/image_resources/logo/teamlogo/8121_small.png",
"time": "4.6.2023 (1:30 AM)",
"url": "",
"live":"0",
"type": "Premium Sever HD,Premium Sever SD",
"premium":"true",
"league": "Ligue 1"
},


{
"id": "2266",
"title": "Nice Vs Lyon",
"img": "https://images.fotmob.com/image_resources/logo/teamlogo/9831_small.png",
"img1": "https://images.fotmob.com/image_resources/logo/teamlogo/9748_small.png",
"time": "4.6.2023 (1:30 AM)",
"url": "",
"live":"0",
"type": "Premium Sever HD,Premium Sever SD",
"premium":"true",
"league": "Ligue 1"
},


{
"id": "2266",
"title": "Paris Saint-Germain Vs Clermont Foot",
"img": "https://images.fotmob.com/image_resources/logo/teamlogo/9847_small.png",
"img1": "https://images.fotmob.com/image_resources/logo/teamlogo/8311_small.png",
"time": "4.6.2023 (1:30 AM)",
"url": "",
"live":"0",
"type": "Premium Sever HD,Premium Sever SD",
"premium":"true",
"league": "Ligue 1"
},


{
"id": "2266",
"title": "Reims Vs Montpellier",
"img": "https://images.fotmob.com/image_resources/logo/teamlogo/9837_small.png",
"img1": "https://images.fotmob.com/image_resources/logo/teamlogo/10249_small.png",
"time": "4.6.2023 (1:30 AM)",
"url": "",
"live":"0",
"type": "Premium Sever HD,Premium Sever SD",
"premium":"true",
"league": "Ligue 1"
},


{
"id": "2266",
"title": "Troyes Vs Lille",
"img": "https://images.fotmob.com/image_resources/logo/teamlogo/10242_small.png",
"img1": "https://images.fotmob.com/image_resources/logo/teamlogo/8639_small.png",
"time": "4.6.2023 (1:30 AM)",
"url": "",
"live":"0",
"type": "Premium Sever HD,Premium Sever SD",
"premium":"true",
"league": "Ligue 1"
}
        








    
    
    ]
   
   }
   
   
